CHANGELOG.txt
MANIFEST.in
README.txt
licence.txt
main.py
requirements.txt
setup.py
docs/conf.py
docs/_build/html/_sources/index.rst.txt
docs/_build/html/_sources/source/api/functions.rst.txt
docs/_build/html/_sources/source/api/index.rst.txt
revamp/__init__.py
revamp/functions.py
revamp.egg-info/PKG-INFO
revamp.egg-info/SOURCES.txt
revamp.egg-info/dependency_links.txt
revamp.egg-info/top_level.txt
tests/__init__.py
tests/functions.py