Metadata-Version: 2.1
Name: revamp
Version: 1.0.0
Summary: Data pre-processing
Home-page: UNKNOWN
Author: Ajeet Rai
Author-email: ajeetrai2293@gmail.com
License: MIT
Keywords: data cleansing
Platform: UNKNOWN
Classifier: Development Status :: 5 - Production/Stable
Classifier: Intended Audience :: Developers
Classifier: Operating System :: Microsoft :: Windows :: Windows 10
Classifier: License :: OSI Approved :: MIT License
Classifier: Programming Language :: Python :: 3
